spytula/__init__.py
spytula/builder.py
spytula/mixins/format.py
spytula-0.0.3.dist-info/METADATA
spytula-0.0.3.dist-info/LICENSE.md
spytula-0.0.3.dist-info/WHEEL
spytula-0.0.3.dist-info/RECORD
