Metadata-Version: 2.1
Name: spytula
Version: 0.0.3
Summary: A Python library that provides a simple and convenient way to build JSON and YAML data structures using a builder pattern.
Home-page: https://github.com/pirhoo/spytula/
License: MIT
Keywords: JSON,YAML,DSL
Author: Pierre Romera
Author-email: hello@pirhoo.com
Requires-Python: >=3.8.1,<4.0.0
Classifier: License :: OSI Approved :: MIT License
Classifier: Programming Language :: Python :: 3
Classifier: Programming Language :: Python :: 3.9
Classifier: Programming Language :: Python :: 3.10
Classifier: Programming Language :: Python :: 3.11
Classifier: Topic :: File Formats :: JSON
Classifier: Topic :: Software Development :: Build Tools
Classifier: Topic :: Software Development :: Libraries :: Python Modules
Requires-Dist: inflection (>=0.5.1,<0.6.0)
Requires-Dist: pytest (>=7.3.2,<8.0.0)
Requires-Dist: pyyaml (>=6.0,<7.0)
Project-URL: Documentation, https://pirhoo.github.io/spytula/
Project-URL: Repository, https://github.com/pirhoo/spytula/
